{
	"id": 3,
	"name": "少女薇拉的忧郁",
	"rank": 4,
	"icon": "UI_ItemIcon_100178",
	"volume": [
		{
			"id": 100178,
			"name": "少女薇拉的忧郁·卷一",
			"description": "我可从来没有觉得世界很无聊。单纯是因为有趣的事情都在很远的地方罢了。\\n——向往着未知远方的平凡少女薇拉，宏大的冒险奇谭悄然开幕。",
			"storyId": "1"
		},
		{
			"id": 100179,
			"name": "少女薇拉的忧郁·卷二",
			"description": "总是在觉得无聊，这可不是什么忧郁，而是到了十四岁年纪了。\\n总之薇拉的冒险，在此开幕！",
			"storyId": "2"
		},
		{
			"id": 100180,
			"name": "少女薇拉的忧郁·卷三",
			"description": "仙女座的帝国幅员辽阔，基本占领了本星系群大半江山。每个行星都有自己的恶魔与众神，海龙与怪兽。\\n「我对你家闪烁的每一个星星都想象过一个故事呢。」「那不可能，这里看仙女座星云只有月亮五分之一大。」\\n少女薇拉的冒险，仍在继续！",
			"storyId": "3"
		},
		{
			"id": 100611,
			"name": "少女薇拉的忧郁·卷四",
			"description": "有句俗话叫，发光的未必是金子，还有可能是因为失恋而破碎的心。\\n总之天上的星星并不是金子，大部分人的心也不是玻璃制成的。\\n总之就是这样，薇拉的冒险，踏入新的篇章！",
			"storyId": "160"
		},
		{
			"id": 100198,
			"name": "少女薇拉的忧郁·卷五",
			"description": "星际高速路和高速公路的路边是不能野餐的，就算是众神被高速星际船撞了也是全责。\\n看起来只是普通的小村书房，透过门扉却可以到达宇宙与时间的任何一处地方！与众神午餐、与时间捉迷藏。薇拉的冒险，在此继续！",
			"storyId": "17"
		},
		{
			"id": 100612,
			"name": "少女薇拉的忧郁·卷六",
			"description": "曾经有一位伟大的学者，想要给帝国的节日写一本著作。\\n结果他发现，好像帝国每一天都有过节的传统！如此巨大的工作量之下，他写了六个月人就跑路了。\\n作者我啊，是不会辜负大家的！",
			"storyId": "161"
		},
		{
			"id": 100613,
			"name": "少女薇拉的忧郁·卷七",
			"description": "在宇宙的边陲的一片星团，可居住的行星密度稀疏。因此这是一片属于星海操帆士和海盗的乐土。\\n因为是宇宙，所以航行没有左舷、右舷。靠着恒星的那一侧叫做星舷。\\n少女薇拉的冒险，在方位感消失的星海继续！",
			"storyId": "162"
		},
		{
			"id": 100614,
			"name": "少女薇拉的忧郁·卷八",
			"description": "女孩子们的睡衣派对环节，男性当然不准参加！可爱的女孩们就像是黄金时代的众神一样，神圣不可方物。\\n薇拉、公主、圣王列班宁，还有星际巢虫的雌性主脑乌尔，四人的少女夜话！",
			"storyId": "163"
		},
		{
			"id": 100199,
			"name": "少女薇拉的忧郁·卷九",
			"description": "「薇拉她这么漂亮，在宇宙里闪耀，而我……」「这个年纪的男孩子看起来就是会比女孩子矮小。」\\n必须得到达青春，必须得告别童年了！事到如今才点题也并不晚，少女薇拉真的开始忧郁！",
			"storyId": "18"
		},
		{
			"id": 100200,
			"name": "少女薇拉的忧郁·卷十",
			"description": "「已经可以了。我们回家吧……现在距离我最远的地方，就是有你的德尔斐。」\\n虽然现在才解释，小镇德尔斐是希腊神话的世界中心。《少女薇拉的忧郁》，圆满完结……吗？",
			"storyId": "19"
		}
	],
	"route": "Vera's Melancholy"
}